Fifo/fifo.v
module fifo
#(
    parameter DATA_WIDTH = 8,  // Data width
    parameter ADDR_WIDTH = 4   // Address width (depth = 2^ADDR_WIDTH)
)
(
    input clk,                 // Clock signal
    input rst,                 // Reset signal
    input wr_en,               // Write enable
    input rd_en,               // Read enable
    input [DATA_WIDTH-1:0] din, // Data input
    output reg [DATA_WIDTH-1:0] dout, // Data output
    output full,               // FIFO full flag
    output empty               // FIFO empty flag
);

    reg [DATA_WIDTH-1:0] fifo_mem [2**ADDR_WIDTH-1:0]; // FIFO memory
    reg [ADDR_WIDTH-1:0] rd_ptr, wr_ptr; // Read and write pointers
    reg fifo_full, fifo_empty; // Status flags

    assign full = fifo_full;
    assign empty = fifo_empty;

    // Write operation
    always @(posedge clk or posedge rst) begin
        if (rst) begin
            wr_ptr <= 0;
        end else if (wr_en && !fifo_full) begin
            fifo_mem[wr_ptr] <= din;
            wr_ptr <= wr_ptr + 1;
        end
    end

    // Read operation
    always @(posedge clk or posedge rst) begin
        if (rst) begin
            rd_ptr <= 0;
        end else if (rd_en && !fifo_empty) begin
            dout <= fifo_mem[rd_ptr];
            rd_ptr <= rd_ptr + 1;
        end
    end

    // Full flag logic
    always @(posedge clk or posedge rst) begin
        if (rst) begin
            fifo_full <= 0;
        end else if (wr_en && (wr_ptr == rd_ptr - 1)) begin
            fifo_full <= 1;
        end else if (rd_en) begin
            fifo_full <= 0;
        end
    end

    // Empty flag logic
    always @(posedge clk or posedge rst) begin
        if (rst) begin
            fifo_empty <= 1;
        end else if (wr_en) begin
            fifo_empty <= 0;
        end else if (rd_en && (rd_ptr == wr_ptr)) begin
            fifo_empty <= 1;
        end
    end

endmodule

Fifo/tb_fifo.v
module tb_fifo;

    parameter DATA_WIDTH = 8;
    parameter ADDR_WIDTH = 4;

    reg clk;
    reg rst;
    reg wr_en;
    reg rd_en;
    reg [DATA_WIDTH-1:0] din;
    wire [DATA_WIDTH-1:0] dout;
    wire full;
    wire empty;

    // Instantiate FIFO
    fifo #(
        .DATA_WIDTH(DATA_WIDTH),
        .ADDR_WIDTH(ADDR_WIDTH)
    ) uut (
        .clk(clk),
        .rst(rst),
        .wr_en(wr_en),
        .rd_en(rd_en),
        .din(din),
        .dout(dout),
        .full(full),
        .empty(empty)
    );

    // Clock generation
    always #5 clk = ~clk; // 10 time units clock period

    // Testbench logic
    initial begin
    
        $dumpfile("tb_fifo.vcd");   // Create a dump file
        $dumpvars(0, tb_fifo);      // Dump all variables in the testbench

        clk = 0;
        rst = 1;
        wr_en = 0;
        rd_en = 0;
        din = 0;

        // Reset FIFO
        #10 rst = 0;

        // Write data into FIFO
        #10 write_fifo(8'hA1);
        #10 write_fifo(8'hB2);
        #10 write_fifo(8'hC3);
        #10 write_fifo(8'hD4);

        // Read data from FIFO
        #10 read_fifo();
        #10 read_fifo();
        #10 read_fifo();
        #10 read_fifo();

        // Fill the FIFO to test full condition
        #10 fill_fifo();

        // Empty the FIFO to test empty condition
        #10 empty_fifo();

        // End simulation
        #50 $finish;
    end

    // Task to write into FIFO
    task write_fifo(input [DATA_WIDTH-1:0] data);
        begin
            if (!full) begin
                din = data;
                wr_en = 1;
                #10 wr_en = 0;
            end else begin
                $display("FIFO is full! Cannot write.");
            end
        end
    endtask

    // Task to read from FIFO
    task read_fifo();
        begin
            if (!empty) begin
                rd_en = 1;
                #10 rd_en = 0;
                $display("Data read from FIFO: %h", dout);
            end else begin
                $display("FIFO is empty! Cannot read.");
            end
        end
    endtask

    // Task to fill FIFO
    task fill_fifo();
        integer i;
        begin
            for (i = 0; i < (2**ADDR_WIDTH); i = i + 1) begin
                write_fifo(i);
            end
        end
    endtask

    // Task to empty FIFO
    task empty_fifo();
        begin
            while (!empty) begin
                read_fifo();
                #10;
            end
        end
    endtask

endmodule

Fifo/tb_fifo.vcd
$date
	Thu Sep 05 13:29:33 2024
$end
$version
	Icarus Verilog
$end
$timescale
	1s
$end
$scope module tb_fifo $end
$var wire 1 ! full $end
$var wire 1 " empty $end
$var wire 8 # dout [7:0] $end
$var parameter 32 $ ADDR_WIDTH $end
$var parameter 32 % DATA_WIDTH $end
$var reg 1 & clk $end
$var reg 8 ' din [7:0] $end
$var reg 1 ( rd_en $end
$var reg 1 ) rst $end
$var reg 1 * wr_en $end
$scope module uut $end
$var wire 1 & clk $end
$var wire 8 + din [7:0] $end
$var wire 1 " empty $end
$var wire 1 ! full $end
$var wire 1 ( rd_en $end
$var wire 1 ) rst $end
$var wire 1 * wr_en $end
$var parameter 32 , ADDR_WIDTH $end
$var parameter 32 - DATA_WIDTH $end
$var reg 8 . dout [7:0] $end
$var reg 1 / fifo_empty $end
$var reg 1 0 fifo_full $end
$var reg 4 1 rd_ptr [3:0] $end
$var reg 4 2 wr_ptr [3:0] $end
$upscope $end
$scope task empty_fifo $end
$upscope $end
$scope task fill_fifo $end
$var integer 32 3 i [31:0] $end
$upscope $end
$scope task read_fifo $end
$upscope $end
$scope task write_fifo $end
$var reg 8 4 data [7:0] $end
$upscope $end
$upscope $end
$enddefinitions $end
$comment Show the parameter values. $end
$dumpall
b1000 -
b100 ,
b1000 %
b100 $
$end
#0
$dumpvars
bx 4
bx 3
b0 2
b0 1
00
1/
bx .
b0 +
0*
1)
0(
b0 '
0&
bx #
1"
0!
$end
#5
1&
#10
0&
0)
#15
1&
#20
0&
1*
b10100001 '
b10100001 +
b10100001 4
#25
0"
0/
b1 2
1&
#30
0&
0*
#35
1&
#40
0&
1*
b10110010 '
b10110010 +
b10110010 4
#45
b10 2
1&
#50
0&
0*
#55
1&
#60
0&
1*
b11000011 '
b11000011 +
b11000011 4
#65
b11 2
1&
#70
0&
0*
#75
1&
#80
0&
1*
b11010100 '
b11010100 +
b11010100 4
#85
b100 2
1&
#90
0&
0*
#95
1&
#100
0&
1(
#105
b1 1
b10100001 #
b10100001 .
1&
#110
0&
0(
#115
1&
#120
0&
1(
#125
b10 1
b10110010 #
b10110010 .
1&
#130
0&
0(
#135
1&
#140
0&
1(
#145
b11 1
b11000011 #
b11000011 .
1&
#150
0&
0(
#155
1&
#160
0&
1(
#165
b100 1
b11010100 #
b11010100 .
1&
#170
0&
0(
#175
1&
#180
0&
1*
b0 '
b0 +
b0 4
b0 3
#185
b101 2
1&
#190
0&
b1 '
b1 +
b1 4
b1 3
1*
#195
b110 2
1&
#200
0&
b10 '
b10 +
b10 4
b10 3
1*
#205
b111 2
1&
#210
0&
b11 '
b11 +
b11 4
b11 3
1*
#215
b1000 2
1&
#220
0&
b100 '
b100 +
b100 4
b100 3
1*
#225
b1001 2
1&
#230
0&
b101 '
b101 +
b101 4
b101 3
1*
#235
b1010 2
1&
#240
0&
b110 '
b110 +
b110 4
b110 3
1*
#245
b1011 2
1&
#250
0&
b111 '
b111 +
b111 4
b111 3
1*
#255
b1100 2
1&
#260
0&
b1000 '
b1000 +
b1000 4
b1000 3
1*
#265
b1101 2
1&
#270
0&
b1001 '
b1001 +
b1001 4
b1001 3
1*
#275
b1110 2
1&
#280
0&
b1010 '
b1010 +
b1010 4
b1010 3
1*
#285
b1111 2
1&
#290
0&
b1011 '
b1011 +
b1011 4
b1011 3
1*
#295
b0 2
1&
#300
0&
b1100 '
b1100 +
b1100 4
b1100 3
1*
#305
b1 2
1&
#310
0&
b1101 '
b1101 +
b1101 4
b1101 3
1*
#315
b10 2
1&
#320
0&
b1110 '
b1110 +
b1110 4
b1110 3
1*
#325
b11 2
1&
#330
0&
b1111 '
b1111 +
b1111 4
b1111 3
1*
#335
b100 2
1!
10
1&
#340
0&
b10000 3
0*
#345
1&
#350
0&
1(
#355
b101 1
b0 #
b0 .
0!
00
1"
1/
1&
#360
0&
0(
